ADBWrapper/__init__.py
ADBWrapper/keycode_enum.py
ADBWrapper-0.0.6.dist-info/METADATA
ADBWrapper-0.0.6.dist-info/WHEEL
ADBWrapper-0.0.6.dist-info/top_level.txt
ADBWrapper-0.0.6.dist-info/RECORD
