Metadata-Version: 2.1
Name: ADBWrapper
Version: 0.0.6
Summary: ADB Wrapper
Home-page: https://github.com/48723247842/ADBWrapper
Author: 7435171
Author-email: 48723247842@protonmail.com
License: UNKNOWN
Platform: UNKNOWN
Classifier: Programming Language :: Python :: 3
Classifier: License :: OSI Approved :: MIT License
Classifier: Operating System :: OS Independent
Requires-Python: >=3.6
Requires-Dist: imagehash (>=4.2.1)
Requires-Dist: Pillow (>=9.1.0)
